hexgen/__init__.py
hexgen/cli.py
hexgen/templates/.gitignore
hexgen/templates/README.md
hexgen/templates/__init__.py
hexgen/templates/aws_deploy.yml
hexgen/templates/custom_config.py
hexgen/templates/dependency_start.py
hexgen/templates/main.py
hexgen/templates/requirements.txt
hexgen/templates/serverless.yaml
hexgen-0.1.3.dist-info/licenses/LICENSE
hexgen-0.1.3.dist-info/METADATA
hexgen-0.1.3.dist-info/WHEEL
hexgen-0.1.3.dist-info/entry_points.txt
hexgen-0.1.3.dist-info/top_level.txt
hexgen-0.1.3.dist-info/RECORD
