Metadata-Version: 2.4
Name: hexgen
Version: 0.1.3
Summary: Gerador de projetos com arquitetura hexagonal
Author-email: Luiz Henrique Rodrigues <luiz.rodrigues.cloud@gmail.com>
License: MIT License
Requires-Python: >=3.8
License-File: LICENSE
Requires-Dist: click>=8.1.0
Requires-Dist: Jinja2>=3.1.0
Dynamic: license-file
